LICENSE
MANIFEST.in
README.md
setup.py
bwsample/__init__.py
bwsample/counting.py
bwsample/maxdiff.py
bwsample/ranking.py
bwsample/sampling.py
bwsample/utils.py
bwsample.egg-info/PKG-INFO
bwsample.egg-info/SOURCES.txt
bwsample.egg-info/dependency_links.txt
bwsample.egg-info/requires.txt
bwsample.egg-info/top_level.txt
bwsample.egg-info/zip-safe
test/__init__.py
test/test_add_dok.py
test/test_adjustscore.py
test/test_count.py
test/test_direct_extract.py
test/test_find_by_state.py
test/test_indices_overlap.py
test/test_indices_twice.py
test/test_logical_infer.py
test/test_logical_infer_update.py
test/test_rank.py
test/test_sample.py
test/test_shuffle_subarrs.py
test/test_to_scipy.py