Metadata-Version: 2.1
Name: bwsample
Version: 0.7.0
Summary: Sampling algorithm for best-worst scaling sets.
Home-page: http://github.com/ulf1/bwsample
Author: Ulf Hamster
Author-email: 554c46@gmail.com
License: Apache License 2.0
Requires-Python: >=3.7
License-File: LICENSE
